{
  "test": 0, 
  "commits": [
    {
      "test": 0, 
      "all": 469, 
      "who": "hiranya", 
      "when": "2011-12-20T05:02:05-05:00", 
      "id": "1221176"
    }, 
    {
      "test": 0, 
      "all": 0, 
      "who": "uswick", 
      "when": "2011-12-20T05:27:36-05:00", 
      "id": "1221187"
    }, 
    {
      "test": 0, 
      "all": 161, 
      "who": "hiranya", 
      "when": "2011-12-20T05:31:15-05:00", 
      "id": "1221190"
    }, 
    {
      "test": 0, 
      "all": 166, 
      "who": "hiranya", 
      "when": "2011-12-20T06:58:12-05:00", 
      "id": "1221214"
    }, 
    {
      "test": 0, 
      "all": 154, 
      "who": "hiranya", 
      "when": "2011-12-20T08:03:47-05:00", 
      "id": "1221242"
    }, 
    {
      "test": 0, 
      "all": 165, 
      "who": "hiranya", 
      "when": "2011-12-20T09:10:39-05:00", 
      "id": "1221265"
    }
  ], 
  "all": 1115
}