{
  "test": 17, 
  "commits": [
    {
      "test": 0, 
      "all": 12, 
      "who": "isudana", 
      "when": "2016-12-25T02:22:25-05:00", 
      "id": "1775996"
    }, 
    {
      "test": 0, 
      "all": 14, 
      "who": "isudana", 
      "when": "2016-12-25T02:32:15-05:00", 
      "id": "1775997"
    }, 
    {
      "test": 0, 
      "all": 289, 
      "who": "isudana", 
      "when": "2016-12-25T11:57:39-05:00", 
      "id": "1776016"
    }, 
    {
      "test": 17, 
      "all": 92, 
      "who": "isudana", 
      "when": "2016-12-25T12:12:21-05:00", 
      "id": "1776017"
    }, 
    {
      "test": 0, 
      "all": 63, 
      "who": "isudana", 
      "when": "2016-12-25T12:38:00-05:00", 
      "id": "1776021"
    }
  ], 
  "all": 470
}